flask_util/__init__.py
flask_util/secure_api.py
flask_util-0.0.1.dev2.dist-info/METADATA
flask_util-0.0.1.dev2.dist-info/WHEEL
flask_util-0.0.1.dev2.dist-info/top_level.txt
flask_util-0.0.1.dev2.dist-info/RECORD
